odoo/addons/fieldservice_sale_order_create_wizard/README.rst
odoo/addons/fieldservice_sale_order_create_wizard/__init__.py
odoo/addons/fieldservice_sale_order_create_wizard/__manifest__.py
odoo/addons/fieldservice_sale_order_create_wizard/i18n/es.po
odoo/addons/fieldservice_sale_order_create_wizard/i18n/fieldservice_sale_order_create_wizard.pot
odoo/addons/fieldservice_sale_order_create_wizard/readme/CONTRIBUTORS.rst
odoo/addons/fieldservice_sale_order_create_wizard/readme/DESCRIPTION.rst
odoo/addons/fieldservice_sale_order_create_wizard/readme/USAGE.rst
odoo/addons/fieldservice_sale_order_create_wizard/security/ir.model.access.csv
odoo/addons/fieldservice_sale_order_create_wizard/static/description/icon.png
odoo/addons/fieldservice_sale_order_create_wizard/static/description/index.html
odoo/addons/fieldservice_sale_order_create_wizard/static/src/js/fsm_create_order_from_kanban.js
odoo/addons/fieldservice_sale_order_create_wizard/static/src/xml/fsm_create_order_from_kanban.xml
odoo/addons/fieldservice_sale_order_create_wizard/tests/__init__.py
odoo/addons/fieldservice_sale_order_create_wizard/tests/test_fsm_so_create_wizard.py
odoo/addons/fieldservice_sale_order_create_wizard/wizard/__init__.py
odoo/addons/fieldservice_sale_order_create_wizard/wizard/fsm_create_so_wizard.py
odoo/addons/fieldservice_sale_order_create_wizard/wizard/fsm_create_so_wizard.xml
odoo_addon_fieldservice_sale_order_create_wizard-15.0.1.1.0.dist-info/METADATA
odoo_addon_fieldservice_sale_order_create_wizard-15.0.1.1.0.dist-info/WHEEL
odoo_addon_fieldservice_sale_order_create_wizard-15.0.1.1.0.dist-info/top_level.txt
odoo_addon_fieldservice_sale_order_create_wizard-15.0.1.1.0.dist-info/RECORD
