Metadata-Version: 2.1
Name: odoo-addon-fieldservice_sale_order_create_wizard
Version: 15.0.1.1.0
Summary: Create Sale Order from Field Service Kanban View
Home-page: https://github.com/OCA/field-service
Author: APSL-Nagarro, Odoo Community Association (OCA)
Author-email: support@odoo-community.org
License: AGPL-3
Classifier: Programming Language :: Python
Classifier: Framework :: Odoo
Classifier: Framework :: Odoo :: 15.0
Classifier: License :: OSI Approved :: GNU Affero General Public License v3
Requires-Python: >=3.8
Requires-Dist: odoo-addon-fieldservice-sale-stock-route<15.1dev,>=15.0dev
Requires-Dist: odoo<15.1dev,>=15.0a
